cef_capi/__init__.py
cef_capi/app_client.py
cef_capi/smoke_test.py
cef_capi/version.py
cef_capi/linux_aarch64/header.py
cef_capi/linux_aarch64/struct.py
cef_capi/linux_aarch64/struct.pyi
cef_capi/linux_x86_64/header.py
cef_capi/linux_x86_64/struct.py
cef_capi/linux_x86_64/struct.pyi
cef_capi/macosx_arm64/header.py
cef_capi/macosx_arm64/struct.py
cef_capi/macosx_arm64/struct.pyi
cef_capi/macosx_x86_64/header.py
cef_capi/macosx_x86_64/struct.py
cef_capi/macosx_x86_64/struct.pyi
cef_capi/runtime/cefclient.app/Contents/Info.plist
cef_capi/runtime/cefclient.app/Contents/PkgInfo
cef_capi/runtime/cefclient.app/Contents/Frameworks/Chromium Embedded Framework.framework/Chromium Embedded Framework
cef_capi/runtime/cefclient.app/Contents/Frameworks/Chromium Embedded Framework.framework/Libraries/libEGL.dylib
cef_capi/runtime/cefclient.app/Contents/Frameworks/Chromium Embedded Framework.framework/Libraries/libGLESv2.dylib
cef_capi/runtime/cefclient.app/Contents/Frameworks/Chromium Embedded Framework.framework/Libraries/libvk_swiftshader.dylib
cef_capi/runtime/cefclient.app/Contents/Frameworks/Chromium Embedded Framework.framework/Libraries/vk_swiftshader_icd.json
cef_capi/runtime/cefclient.app/Contents/Frameworks/Chromium Embedded Framework.framework/Resources/Info.plist
cef_capi/runtime/cefclient.app/Contents/Frameworks/Chromium Embedded Framework.framework/Resources/chrome_100_percent.pak
cef_capi/runtime/cefclient.app/Contents/Frameworks/Chromium Embedded Framework.framework/Resources/chrome_200_percent.pak
cef_capi/runtime/cefclient.app/Contents/Frameworks/Chromium Embedded Framework.framework/Resources/gpu_shader_cache.bin
cef_capi/runtime/cefclient.app/Contents/Frameworks/Chromium Embedded Framework.framework/Resources/icudtl.dat
cef_capi/runtime/cefclient.app/Contents/Frameworks/Chromium Embedded Framework.framework/Resources/resources.pak
cef_capi/runtime/cefclient.app/Contents/Frameworks/Chromium Embedded Framework.framework/Resources/snapshot_blob.bin
cef_capi_py-131.3.5.dist-info/LICENSE
cef_capi_py-131.3.5.dist-info/METADATA
cef_capi_py-131.3.5.dist-info/WHEEL
cef_capi_py-131.3.5.dist-info/top_level.txt
cef_capi_py-131.3.5.dist-info/RECORD
