Metadata-Version: 2.2
Name: cef-capi-py
Version: 131.3.5
Summary: Chromium Embedded Framework (CEF) C API wrapper for Python without C extension, with ctypes
Author-email: NAKAZATO Hajime <hajime@kaoriha.org>
License: MIT License
Project-URL: repository, https://github.com/hajimen/cef-capi-py.git
Keywords: CEF,Chromium Embedded Framework,ctypes
Classifier: Development Status :: 3 - Alpha
Classifier: Intended Audience :: Developers
Classifier: Topic :: Software Development :: Libraries :: Python Modules
Classifier: License :: OSI Approved :: MIT License
Classifier: Programming Language :: Python :: 3
Classifier: Programming Language :: Python :: 3.11
Classifier: Programming Language :: Python :: 3.12
Classifier: Programming Language :: Python :: 3.13
Requires-Python: >=3.11
License-File: LICENSE
